plotly_agent/__init__.py
plotly_agent/agent.py
plotly_agent/detect.py
plotly_agent/evaluate/__init__.py
plotly_agent/evaluate/judge_text.py
plotly_agent/extract.py
plotly_agent/toolkit.py
plotly_agent-0.1.6.dist-info/LICENSE
plotly_agent-0.1.6.dist-info/METADATA
plotly_agent-0.1.6.dist-info/WHEEL
plotly_agent-0.1.6.dist-info/RECORD
