Metadata-Version: 2.1
Name: plotly-agent
Version: 0.1.6
Summary: Visualize your data with Langchain and Plotly through a Plotly agent
License: MIT
Author: Lucas Lago
Author-email: lukemartinslagonit@gmail.com
Requires-Python: >=3.11,<4.0
Classifier: License :: OSI Approved :: MIT License
Classifier: Programming Language :: Python :: 3
Classifier: Programming Language :: Python :: 3.11
Classifier: Programming Language :: Python :: 3.12
Requires-Dist: langchain (>=0.2.11,<0.3.0)
Requires-Dist: nbformat (>=5.10.4,<6.0.0)
Requires-Dist: pandas (>=2.2.2,<3.0.0)
Requires-Dist: plotly (>=5.23.0,<6.0.0)
